sammoo/__init__.py
sammoo/config_selection.py
sammoo/parmoo_simulation.py
sammoo/version.py
sammoo/resources/collector_data/iph_collectors_parameters.csv
sammoo/resources/solar_resource/seville_spain_37.377N_-5.926W_hourly.csv
sammoo/templates/iph_parabolic_commercial_owner/default_cashloan_heat.json
sammoo/templates/iph_parabolic_commercial_owner/default_thermalrate_iph.json
sammoo/templates/iph_parabolic_commercial_owner/default_trough_physical_iph.json
sammoo/templates/iph_parabolic_commercial_owner/default_utilityrate5.json
sammoo-0.2.0.dist-info/licenses/LICENSE
sammoo-0.2.0.dist-info/METADATA
sammoo-0.2.0.dist-info/WHEEL
sammoo-0.2.0.dist-info/top_level.txt
sammoo-0.2.0.dist-info/RECORD
