Metadata-Version: 2.4
Name: sammoo
Version: 0.2.0
Summary: Python-based framework for multi-objective optimization of renewable energy systems using NREL's System Advisor Model (SAM)
Author-email: Pedro Padilla Quesada <pedro_padilla_q@hotmail.com>
License: BSD-3-Clause
Requires-Python: >=3.10
License-File: LICENSE
Requires-Dist: numpy
Requires-Dist: NREL-PySAM
Requires-Dist: parmoo
Requires-Dist: matplotlib
Dynamic: license-file
